{
  "hargaEmas": {
    "38 Juene": 640000,
    "44 Kuning": 715000,
    "44 Kuningcoll": 715000, 
    "46 Putih": 750000,
    "48 Kuning": 780000,
    "48 Kuningcoll": 780000, 
    "49 Putih": 795000,
    "75 16K": 1229000,
    "75 16Kwg": 1229000, 
    "81-89 17K": 1357000, 
    "81-89 17Kyg": 1357000,
    "46.5 8K": 720000,
    "54 VC ILY": 878000,
    "16K coll": 1261000,
    "17K coll": 1389000,
    "Italy": 1580500,
    "SDW": 1468500,
    "84.5 : 0",
    "85.5 : 0",
    "86.5 : 0",
    "87.5 : 0",
    "88.5 : 0",
    "89.5 : 0",
    "90.5 : 0"
  }
}
